{
    "app-id": "org.gnome.Totem.Devel",
    "runtime": "org.gnome.Platform",
    "runtime-version": "master",
    "sdk": "org.gnome.Sdk",
    "command": "totem",
    "tags": ["nightly"],
    "finish-args": [
        /* X11 + XShm access */
        "--share=ipc", "--socket=fallback-x11",
        /* Wayland access */
        "--socket=wayland",
        /* OpenGL access */
        "--device=dri",
        /* Needs to talk to the network: */
        "--share=network",
        /* Online accounts support */
        "--talk-name=org.gnome.OnlineAccounts",
        /* Avahi */
        "--system-talk-name=org.freedesktop.Avahi",
        /* DLNA server */
        "--talk-name=com.intel.dleyna-server",
        /* Play sounds */
        "--socket=pulseaudio",
        /* Browse user's Videos directory and Downloads */
        "--filesystem=xdg-videos",
        "--filesystem=xdg-download",
        /* Browse gvfs */
        "--talk-name=org.gtk.vfs.*",
        "--filesystem=xdg-run/gvfs", "--filesystem=xdg-run/gvfsd",
        /* screensaver plugin */
        "--talk-name=org.gnome.ScreenSaver",
        /* screenshot plugin */
        "--talk-name=org.gnome.Shell",
        /* save-file plugin */
        "--talk-name=org.gnome.Nautilus",
        /* MPRIS plugin */
        "--own-name=org.mpris.MediaPlayer2.totem",
        /* im-status plugin */
        "--talk-name=org.gnome.SessionManager"
    ],
    "cleanup": [ "/include", "/share/bash-completion" ],
    "modules": [
        "shared-modules/lua5.4/lua-5.4.json",
        {
            "name": "libsoup-2.4",
            "buildsystem": "meson",
            "config-opts": [
                "-Dvapi=disabled",
                "-Dtests=false",
                "-Dtls_check=false",
                "-Dntlm=disabled",
                "-Dsysprof=enabled"
            ],
            "sources": [
                {
                    "type": "git",
                    "url": "https://gitlab.gnome.org/GNOME/libsoup.git",
                    "branch": "libsoup-2-74"
                }
            ]
        },
        {
            "name": "gnome-common",
            "sources": [
                {
                    "type": "git",
                    "url": "https://gitlab.gnome.org/GNOME/gnome-common.git"
                }
            ]
        },
        {
            "name": "intltool",
            "cleanup": [ "*" ],
            "sources": [
                {
                    "type": "archive",
                    "url": "https://launchpad.net/intltool/trunk/0.51.0/+download/intltool-0.51.0.tar.gz",
                    "sha256": "67c74d94196b153b774ab9f89b2fa6c6ba79352407037c8c14d5aeb334e959cd"
                }
            ]
        },
        {
            "name": "libpeas",
            "buildsystem": "meson",
            "config-opts": [ "-Dwidgetry=false" ],
            "sources": [
                {
                    "type": "git",
                    "url": "https://gitlab.gnome.org/GNOME/libpeas.git"
                }
            ]
        },
        {
            "name": "totem-pl-parser",
            "buildsystem": "meson",
            "sources": [
                {
                    "type": "git",
                    "url": "https://gitlab.gnome.org/GNOME/totem-pl-parser.git"
                }
            ],
            "cleanup": [ "/include" ]
        },
        {
            "name": "grilo",
            "buildsystem": "meson",
            "config-opts": [
                "-Denable-grl-net=true",
                "-Dsoup3=false",
                "-Denable-grl-pls=true"
            ],
            "sources": [
                {
                    "type": "git",
                    "url": "https://gitlab.gnome.org/GNOME/grilo.git"
                }
            ],
            "cleanup": [ "/include" ]
        },
        {
            "name": "librest",
            "buildsystem": "meson",
            "config-opts": [ "-Dgtk_doc=false", "-Dtests=false", "-Dexamples=false" ],
            "sources": [
                {
                    "type": "git",
                    "url": "https://gitlab.gnome.org/GNOME/librest.git"
                }
            ]
        },
        {
            "name": "gnome-online-accounts",
            "buildsystem": "meson",
            "config-opts": [ "-Dgtk_doc=false", "-Dgoabackend=false", "-Dman=false" ],
            "sources": [
                {
                    "type": "git",
                    "url": "https://gitlab.gnome.org/GNOME/gnome-online-accounts.git"
                }
            ]
        },
        {
            "name": "liboauth",
            "config-opts": [ "--enable-nss" ],
            "cleanup": [ "/bin/*oauth*", "share/man/man1/*oauth*" ],
            "sources": [
                {
                    "type": "archive",
                    "url": "http://netix.dl.sourceforge.net/project/liboauth/liboauth-1.0.3.tar.gz",
                    "sha256": "0df60157b052f0e774ade8a8bac59d6e8d4b464058cc55f9208d72e41156811f"
                }
            ]
        },
        {
            "name": "libgdata",
            "buildsystem": "meson",
            "config-opts": [
                 "-Dalways_build_tests=false",
                 "-Dgtk=disabled",
                 "-Dgtk_doc=false",
                 "-Dinstalled_tests=false",
                 "-Dintrospection=false",
                 "-Dvapi=false"
            ],
            "sources": [
                {
                    "type": "git",
                    "url": "https://gitlab.gnome.org/GNOME/libgdata.git",
                    "branch": "main"
                }
            ]
        },
        {
            "name": "gom",
            "buildsystem": "meson",
            "config-opts": [ "-Denable-introspection=false" ],
            "sources": [
                {
                    "type": "git",
                    "url": "https://gitlab.gnome.org/GNOME/gom.git"
                }
            ]
        },
        {
            "name": "tracker-miners",
            "cleanup": [ "/bin", "/etc" ],
            "buildsystem": "meson",
            "config-opts" : [
                "-Dman=false",
                "-Dminer_fs=true",
                "-Dminer_rss=false",
                "-Dsystemd_user_services=false",
                "-Dwriteback=false",
                "-Ddomain_prefix=org.gnome.Totem.Devel",
                "-Dminer_fs_cache_location=$XDG_CACHE_HOME/totem/miner/files",
                "-Ddefault_index_recursive_dirs=['&VIDEOS']",
                "-Ddefault_index_single_dirs=['&DOWNLOAD']"
            ],
            "sources": [
                {
                    "type": "git",
                    "url": "https://gitlab.gnome.org/GNOME/tracker-miners.git"
                }
            ]
        },
        {
            "name": "libmediaart",
            "cleanup": [ "/bin", "/etc", "/libexec" ],
            "buildsystem": "meson",
            "config-opts": [ "-Dimage_library=gdk-pixbuf" ],
            "sources": [
                {
                    "type": "git",
                    "url": "https://gitlab.gnome.org/GNOME/libmediaart.git"
                }
            ]
        },
        {
            "name": "avahi",
            "cleanup": [ "/bin/*avahi*", "share/man/man1/*avahi*" ],
            "config-opts": [
                "--with-distro=none",
                "--enable-gobject",
                "--with-xml=expat",
                "--disable-libdaemon",
                "--disable-core-docs",
                "--disable-manpages",
                "--disable-mono",
                "--disable-qt3",
                "--disable-qt4",
                "--disable-python",
                "--disable-gtk",
                "--disable-gtk3"
            ],
            "sources": [
                {
                    "type": "archive",
                    "url": "https://avahi.org/download/avahi-0.7.tar.gz",
                    "sha256": "57a99b5dfe7fdae794e3d1ee7a62973a368e91e414bd0dfa5d84434de5b14804"
                }
            ]
        },
        /* XXX Remove the Lua sources we won't use */
        {
            "name": "grilo-plugins",
            "buildsystem": "meson",
            "config-opts": [
                "-Denable-filesystem=yes",
                "-Denable-optical-media=yes",
                "-Denable-youtube=yes",
                "-Denable-bookmarks=yes",
                "-Denable-lua-factory=yes",
                "-Denable-metadata-store=yes",
                "-Denable-tracker=no",
                "-Denable-tracker3=yes",
                "-Denable-local-metadata=yes",
                "-Denable-dleyna=yes",
                "-Denable-thetvdb=yes",
                "-Denable-tmdb=yes",
                "-Denable-freebox=yes",
                "-Denable-opensubtitles=yes"
            ],
            "sources": [
                {
                    "type": "git",
                    "url": "https://gitlab.gnome.org/GNOME/grilo-plugins.git"
                }
            ],
            "cleanup": [ "/include" ]
        },
        {
            "name": "gnome-desktop",
            "buildsystem": "meson",
            "config-opts": ["-Ddebug_tools=false", "-Dudev=disabled"],
            "sources": [
                {
                    "type": "git",
                    "url": "https://gitlab.gnome.org/GNOME/gnome-desktop.git"
                }
            ]
        },
        {
            "name" : "libhandy",
            "buildsystem" : "meson",
            "config-opts" : [
                "-Dexamples=false",
                "-Dglade_catalog=disabled",
                "-Dtests=false"
            ],
            "sources" : [
                {
                    "type": "git",
                    "url": "https://gitlab.gnome.org/GNOME/libhandy",
                    "branch": "main"
                }
            ]
        },
        {
            "name": "totem",
            "buildsystem": "meson",
            "config-opts": [
                "-Denable-easy-codec-installation=no",
                "-Dinspector-page=true",
                "-Dprofile=development"
            ],
            "sources": [
                {
                    "type": "git",
                    "url": "https://gitlab.gnome.org/GNOME/totem.git"
                }
            ]
        }
    ]
}
